{
    "@type": "CommandLineTool",
    "@context": "https://raw.githubusercontent.com/common-workflow-language/common-workflow-language/draft-2-pa/schemas/draft-2/context.json",
    "description": "Print the contents of a file to stdout using 'cat' running in a docker container.",
    "requirements": [
        {
          "requirementType": "DockerContainer",
          "dockerPull": "arvados/jobs"
        }
    ],
    "inputs": [
        {
            "port": "#file1",
            "type": "File"
        }
    ],
    "outputs": [],
    "baseCommand": "cat",
    "stdin": {
        "expressionType": "javascript",
        "value": "$job.file1.path"
    }
}
